swarmsort/__init__.py
swarmsort/archive_algo/core2D.py
swarmsort/archive_algo/core3D.py
swarmsort/benchmarking.py
swarmsort/config.py
swarmsort/core.py
swarmsort/data_classes.py
swarmsort/drawing_utils.py
swarmsort/embedding_scaler.py
swarmsort/embeddings.py
swarmsort/integration.py
swarmsort/prepare_input.py
swarmsort/simulator.py
swarmsort/swarmtracker_adapter.py
swarmsort-1.1.0.dist-info/LICENSE
swarmsort-1.1.0.dist-info/METADATA
swarmsort-1.1.0.dist-info/WHEEL
swarmsort-1.1.0.dist-info/RECORD
