Metadata-Version: 2.3
Name: swarmsort
Version: 1.1.0
Summary: Standalone SwarmSort real-time multi-object tracker with integrated lightweight embeddings
License: GPL-3.0-or-later
Keywords: tracking,computer-vision,multi-object-tracking,embeddings,real-time
Author: Charles Fosseprez
Author-email: charles.fosseprez.pro@gmail.com
Requires-Python: >=3.9,<3.12
Classifier: Development Status :: 3 - Alpha
Classifier: Intended Audience :: Developers
Classifier: Intended Audience :: Science/Research
Classifier: License :: OSI Approved :: GNU General Public License v3 or later (GPLv3+)
Classifier: Programming Language :: Python :: 3
Classifier: Programming Language :: Python :: 3.9
Classifier: Programming Language :: Python :: 3.10
Classifier: Programming Language :: Python :: 3.11
Classifier: Topic :: Scientific/Engineering :: Artificial Intelligence
Classifier: Topic :: Scientific/Engineering :: Image Recognition
Provides-Extra: gpu
Provides-Extra: gpu11
Provides-Extra: plotting
Requires-Dist: cupy-cuda11x (>=12.0.0,<13.0.0) ; extra == "gpu11"
Requires-Dist: cupy-cuda12x (>=12.0.0,<13.0.0) ; extra == "gpu"
Requires-Dist: loguru (>=0.7.0,<0.8.0)
Requires-Dist: matplotlib (>=3.7.0,<4.0.0) ; extra == "plotting"
Requires-Dist: numba (>=0.57.0,<0.58.0)
Requires-Dist: numpy (>=1.24.0,<2.0.0)
Requires-Dist: opencv-python (>=4.8.0,<5.0.0)
Requires-Dist: pyyaml (>=6.0,<7.0)
Requires-Dist: scipy (>=1.10.0,<2.0.0)
Requires-Dist: tqdm (>=4.66.1,<5.0.0)
Project-URL: Homepage, https://github.com/cfosseprez/swarmsort
Project-URL: Repository, https://github.com/cfosseprez/swarmsort
